tridentweb/__init__.py
tridentweb/tridentweb.py
tridentweb-0.0.1.dev1.dist-info/METADATA
tridentweb-0.0.1.dev1.dist-info/WHEEL
tridentweb-0.0.1.dev1.dist-info/entry_points.txt
tridentweb-0.0.1.dev1.dist-info/top_level.txt
tridentweb-0.0.1.dev1.dist-info/RECORD
